{
  "title": "Nova Clicker",
  "category": "casual",
  "tags": [
    "1-player",
    "2d",
    "clicker",
    "crazy",
    "free",
    "funny",
    "html5",
    "idle",
    "mobile",
    "mouse"
  ],
  "iframeUrl": "https://cloud.onlinegames.io/games/2024/construct/314/nova-clicker/index-og.html",
  "coverImage": "https://www.onlinegames.io/media/posts/981/responsive/Nova-Clicker-xs.jpg",
  "description": "Nova Clicker is an online idle game which starts you off with a single, smiley Nova, its name is FreezeNova.  A simple tap or click on FreezeNova produces your first handful of stars.  But don't be fooled, this clicker game quickly grows beyond basic tapping.  Soon, you'll be managing an entire universe of quirky characters and powerful upgrades, all designed to make you the ultimate star tycoon.",
  "slug": "nova-clicker"
}