{
  "title": "Crazy Karts",
  "category": "action",
  "tags": [
    "3d",
    "battle",
    "battle-royale",
    "crazy",
    "destroy",
    "driving",
    "free",
    "fun",
    "io-games",
    "kart",
    "multiplayer",
    "unity"
  ],
  "iframeUrl": "https://www.onlinegames.io/games/2024/unity/crazy-karts/index.html",
  "coverImage": "https://www.onlinegames.io/media/posts/740/responsive/Crazy-Karts-xs.jpg",
  "description": "Did you know that most Formula 1 drivers started their careers with Karting?  These tiny four-wheeled machines can reach speeds of up to 100 mph.  \nEven though karting is an adrenaline-pumping experience as you drive a lightweight vehicle on a crazy circuit, drivers are open to many safety risks.  That's why we bring this experience to the virtual realm.",
  "slug": "crazy-karts"
}