{
  "title": "Princesses Prom Night",
  "category": "io",
  "tags": [
    "2d",
    "dress-up",
    "fashion",
    "free",
    "girl",
    "html5",
    "kids",
    "makeup",
    "mobile",
    "mouse",
    "princess"
  ],
  "iframeUrl": "https://www.onlinegames.io/games/2021/3/princesses-prom-night/index.html",
  "coverImage": "https://www.onlinegames.io/media/posts/498/responsive/Princesses-Prom-Night-xs.jpg",
  "description": "It's your responsibility to prepare the girls for the most important night of their lives!  Princesses Prom Night is a girl game where your task is to prepare these princesses for their magical prom night.  It's the end of the academic year for the princesses, and the prom night they've been waiting for.  Everyone's eyes are on you to prepare them!",
  "slug": "princesses-prom-night"
}