{
  "title": "Draw Here",
  "category": "puzzle",
  "tags": [
    "1-player",
    "2d",
    "brain",
    "drawing",
    "free",
    "logic",
    "mobile",
    "physics",
    "puzzle"
  ],
  "iframeUrl": "https://www.onlinegames.io/games/2021/unity2/draw-here/index.html",
  "coverImage": "https://www.onlinegames.io/media/posts/567/responsive/Draw-Here-xs.jpg",
  "description": "Draw Here is a physics puzzle game with 100 levels.  Draw objects on the canvas to collect all the stars.  Use your basic physics knowledge besides drawing skills.  Gravity, motion and energy conversion are all in this game.",
  "slug": "draw-here"
}